easydcer/__init__.py
easydcer/__main__.py
easydcer/easydcer.py
easydcer/easydcer_modules/__init__.py
easydcer/easydcer_modules/basicChecks.py
easydcer/easydcer_modules/config.py
easydcer/easydcer_modules/dcer.py
pyeasydcer-1.4.1.dist-info/LICENSE
pyeasydcer-1.4.1.dist-info/METADATA
pyeasydcer-1.4.1.dist-info/WHEEL
pyeasydcer-1.4.1.dist-info/entry_points.txt
pyeasydcer-1.4.1.dist-info/top_level.txt
pyeasydcer-1.4.1.dist-info/RECORD
