Metadata-Version: 2.1
Name: pyeasydcer
Version: 1.4.1
Summary: Easy way to import default content in Drupal 8 using python
Home-page: https://github.com/ruthvikvegunta/pyeasydcer/
Author: Ruthvik Vegunta
Author-email: ruthvikv@icloud.com, ruthvikvegunta2@gmail.com
License: MIT
Keywords: Drupal,Default Content,dcer,easydcer
Platform: UNKNOWN
Classifier: License :: OSI Approved :: MIT License
Classifier: Programming Language :: Python :: 3.7
Requires-Python: >=3.7
